yamaplotutil/__init__.py
yamaplotutil/dtypes.py
yamaplotutil/fileReader.py
yamaplotutil/fitfunctions.py
yamaplotutil/functions.py
yamaplotutil-0.0.2.dist-info/METADATA
yamaplotutil-0.0.2.dist-info/WHEEL
yamaplotutil-0.0.2.dist-info/licenses/LICENSE
yamaplotutil-0.0.2.dist-info/RECORD
